{
  "success": true,
  "data": [
    {
      "id": "e2d5aed4-98f0-4846-a6ab-147c156609e7",
      "artistName": "All One",
      "imageUrl": "https://i.scdn.co/image/ab6761610000e5eb0c8fa1819db3cf0850a4e6b8",
      "spotifyUrl": "https://open.spotify.com/artist/1YFqP7Bw1SBL1xjFCQM940",
      "spotifyId": "1YFqP7Bw1SBL1xjFCQM940",
      "status": "active",
      "joinedDate": "2025-06-01T21:27:52.079183+00:00"
    },
    {
      "id": "8e2bdba3-026a-49f4-8fd0-14748f91fbd7",
      "artistName": "Anne Noor",
      "imageUrl": "https://i.scdn.co/image/ab6761610000e5eb9927c19c526f327b467e3c01",
      "spotifyUrl": "https://open.spotify.com/artist/6V2aXvr8dsRc60wVG9cdU8",
      "spotifyId": "6V2aXvr8dsRc60wVG9cdU8",
      "status": "active",
      "joinedDate": "2025-06-01T21:27:52.079183+00:00"
    },
    {
      "id": "031de3ab-055e-4a87-a3de-7152b69329d2",
      "artistName": "BATU (TR)",
      "imageUrl": "https://i.scdn.co/image/ab6761610000e5ebde794662091bd5aaaf6d4085",
      "spotifyUrl": "https://open.spotify.com/artist/4bRac4iORCXK0jWtdCOdJL",
      "instagramUrl": "https://www.instagram.com/batu.ofc/",
      "spotifyId": "4bRac4iORCXK0jWtdCOdJL",
      "status": "active",
      "joinedDate": "2025-06-01T21:27:52.079183+00:00"
    },
    {
      "id": "b7716ddb-0027-4bd0-ac66-93db9987a13b",
      "artistName": "Black Culture",
      "imageUrl": "https://i.scdn.co/image/ab6761610000e5ebc3794b5a9df078b65debf8f2",
      "spotifyUrl": "https://open.spotify.com/artist/2331I1TOUrGnlIbG8Vs1gp",
      "appleMusicUrl": "https://music.apple.com/se/artist/black-culture/1652598210?l=en-GB$0",
      "spotifyId": "2331I1TOUrGnlIbG8Vs1gp",
      "status": "active",
      "joinedDate": "2025-06-01T21:27:52.079183+00:00"
    },
    {
      "id": "2d0f0eb4-f382-43ef-a9eb-709ddf087e66",
      "artistName": "Bongi Silinda",
      "imageUrl": "https://i.scdn.co/image/ab6761610000e5eb56544f3d1581a8ba610e6522",
      "spotifyUrl": "https://open.spotify.com/artist/1HS4J0XmZ1djkEOtCkhH6r",
      "spotifyId": "1HS4J0XmZ1djkEOtCkhH6r",
      "status": "active",
      "joinedDate": "2025-06-01T21:27:52.079183+00:00"
    },
    {
      "id": "14f6181e-9a9c-4a22-9889-a39b64dd224c",
      "artistName": "Bukeka",
      "imageUrl": "https://i.scdn.co/image/ab6761610000e5ebfc4040645c2dbc0268e4114d",
      "spotifyUrl": "https://open.spotify.com/artist/3pHdLWNBGYLGZLMB8cuFOV",
      "spotifyId": "3pHdLWNBGYLGZLMB8cuFOV",
      "status": "active",
      "joinedDate": "2025-06-01T21:27:52.079183+00:00"
    },
    {
      "id": "d3b715ca-af1e-4962-9c15-2fcc8f4718e6",
      "artistName": "C-Mart",
      "imageUrl": "https://i.scdn.co/image/ab6761610000e5eb7acf686c4beb82bb35386690",
      "spotifyUrl": "https://open.spotify.com/artist/5Gp2z5HyXJ8ezC5if2DlXk",
      "instagramUrl": "https://www.instagram.com/officialcmart/",
      "appleMusicUrl": "https://music.apple.com/se/artist/c-mart/1206308644?l=en-GB",
      "spotifyId": "5Gp2z5HyXJ8ezC5if2DlXk",
      "status": "active",
      "joinedDate": "2025-06-01T21:27:52.079183+00:00"
    },
    {
      "id": "1d2f71e6-e936-434e-ac92-4578dda4d7e3",
      "artistName": "David Puentez",
      "imageUrl": "https://i.scdn.co/image/ab6761610000e5ebd2232e31e0002c2429e91f5b",
      "spotifyUrl": "https://open.spotify.com/artist/4gSsv9FQDyXx0GUkZYha7v",
      "spotifyId": "4gSsv9FQDyXx0GUkZYha7v",
      "status": "active",
      "joinedDate": "2025-06-01T21:27:52.079183+00:00"
    },
    {
      "id": "223ec715-3425-472a-9ced-7bc66a45a2f1",
      "artistName": "Double MZK",
      "imageUrl": "https://i.scdn.co/image/ab6761610000e5eb0637b3206f6e79fb438300be",
      "spotifyUrl": "https://open.spotify.com/artist/6xacomOfO7szsy6qZanBtI",
      "spotifyId": "6xacomOfO7szsy6qZanBtI",
      "status": "active",
      "joinedDate": "2025-06-01T21:27:52.079183+00:00"
    },
    {
      "id": "8f6611c8-0a68-40f5-93eb-01942176d38d",
      "artistName": "Drega",
      "imageUrl": "https://i.scdn.co/image/ab6761610000e5ebe6f500db21252404c9b1b7db",
      "spotifyUrl": "https://open.spotify.com/artist/1Gj6W2RfGpl6ebJGle93VG",
      "spotifyId": "1Gj6W2RfGpl6ebJGle93VG",
      "status": "active",
      "joinedDate": "2025-06-01T21:27:52.079183+00:00"
    },
    {
      "id": "b1061492-fa42-4097-a7e4-be19e49cfed5",
      "artistName": "Engeloop",
      "imageUrl": "https://i.scdn.co/image/ab6761610000e5ebd48fc0fe7628af91f7929bc3",
      "spotifyUrl": "https://open.spotify.com/artist/24zkRmCAIWFntopvfFXBkd",
      "spotifyId": "24zkRmCAIWFntopvfFXBkd",
      "status": "active",
      "joinedDate": "2025-06-01T21:27:52.079183+00:00"
    },
    {
      "id": "b4054a3a-49a9-4810-a94f-3be8f3df030a",
      "artistName": "Flightrisk",
      "imageUrl": "https://i.scdn.co/image/ab6761610000e5eb3644de18ec0b6ef6d7d6864c",
      "spotifyUrl": "https://open.spotify.com/artist/62HEzthPdINsfpkecdrWdI",
      "spotifyId": "62HEzthPdINsfpkecdrWdI",
      "status": "active",
      "joinedDate": "2025-06-01T21:27:52.079183+00:00"
    },
    {
      "id": "dc2427ef-e7e8-48ac-8a36-91b5f7aa7fa0",
      "artistName": "Frances Shelley",
      "imageUrl": "https://i.scdn.co/image/ab6761610000e5eb1dc4f6a19b79492bb4fdce37",
      "spotifyUrl": "https://open.spotify.com/artist/0oUU96ZHc648yvAP9JrQ9d",
      "spotifyId": "0oUU96ZHc648yvAP9JrQ9d",
      "status": "active",
      "joinedDate": "2025-06-01T21:27:52.079183+00:00"
    },
    {
      "id": "c776288f-8ac7-43e2-94d6-4e825ae7f0e0",
      "artistName": "Geeyo Ibra",
      "imageUrl": "https://i.scdn.co/image/ab6761610000e5ebe3ed04f6f654d6ec5a2286ba",
      "spotifyUrl": "https://open.spotify.com/artist/7qNEEQYlCIDFev1Z297wdx",
      "spotifyId": "7qNEEQYlCIDFev1Z297wdx",
      "status": "active",
      "joinedDate": "2025-06-01T21:27:52.079183+00:00"
    },
    {
      "id": "48d38b79-00f7-4627-b766-d216650ad081",
      "artistName": "Glory",
      "imageUrl": "https://i.scdn.co/image/ab6761610000e5ebc87b1487f60d3023aae87cd9",
      "spotifyUrl": "https://open.spotify.com/artist/0YlcGZCtFX56RYjJqyh0ut",
      "instagramUrl": "https://www.instagram.com/glory.music/",
      "spotifyId": "0YlcGZCtFX56RYjJqyh0ut",
      "status": "active",
      "joinedDate": "2025-06-01T21:27:52.079183+00:00"
    },
    {
      "id": "eeffe823-6fcb-4273-9712-d04f8a37449f",
      "artistName": "Hacelen Royer",
      "imageUrl": "https://i.scdn.co/image/ab6761610000e5eb6172dceefe8f705ae900c435",
      "spotifyUrl": "https://open.spotify.com/artist/53Gx9TZKzSLf13rNNC7dlj",
      "spotifyId": "53Gx9TZKzSLf13rNNC7dlj",
      "status": "active",
      "joinedDate": "2025-06-01T21:27:52.079183+00:00"
    },
    {
      "id": "2e477230-f188-4696-ab1d-d4879fb22a1b",
      "artistName": "Idd Aziz",
      "imageUrl": "https://i.scdn.co/image/ab6761610000e5eb9e03d30227a68dbb4fc3e649",
      "spotifyUrl": "https://open.spotify.com/artist/0LC3HTEh3afI3UfpmSdShk",
      "spotifyId": "0LC3HTEh3afI3UfpmSdShk",
      "status": "active",
      "joinedDate": "2025-06-01T21:27:52.079183+00:00"
    },
    {
      "id": "2f442f54-1d4f-44df-a60f-a219efd0495c",
      "artistName": "Instant Touch SA",
      "imageUrl": "https://i.scdn.co/image/ab6761610000e5ebad7e8040a20335532f2250c8",
      "spotifyUrl": "https://open.spotify.com/artist/19KmTb9GBqJfPkjbPl2Huo",
      "spotifyId": "19KmTb9GBqJfPkjbPl2Huo",
      "status": "active",
      "joinedDate": "2025-06-01T21:27:52.079183+00:00"
    },
    {
      "id": "972655cf-3ba4-4bc6-a1e9-56f8b8e860cc",
      "artistName": "J Fitz",
      "imageUrl": "https://i.scdn.co/image/ab6761610000e5eb5064786d016a243e7a5142d6",
      "spotifyUrl": "https://open.spotify.com/artist/5fO3cjaQXn3DpDsxlJbmQJ",
      "spotifyId": "5fO3cjaQXn3DpDsxlJbmQJ",
      "status": "active",
      "joinedDate": "2025-06-01T21:27:52.079183+00:00"
    },
    {
      "id": "c7390fc4-7909-4f7c-a820-67ce24f59e94",
      "artistName": "JANAKEY",
      "imageUrl": "https://i.scdn.co/image/ab6761610000e5ebbf6c0ee83b9331137ce39242",
      "spotifyUrl": "https://open.spotify.com/artist/24udzsxakjNTTMYETGtOMx",
      "spotifyId": "24udzsxakjNTTMYETGtOMx",
      "status": "active",
      "joinedDate": "2025-06-01T21:27:52.079183+00:00"
    },
    {
      "id": "a1481f8d-fe5c-47d9-ad0b-975fbbc05e9e",
      "artistName": "JANAKEY",
      "imageUrl": "https://i.scdn.co/image/ab6761610000e5ebbf6c0ee83b9331137ce39242",
      "spotifyUrl": "https://open.spotify.com/artist/24udzsxakjNTTMYETGtOMx",
      "spotifyId": "24udzsxakjNTTMYETGtOMx",
      "status": "active",
      "joinedDate": "2025-06-01T21:27:52.079183+00:00"
    },
    {
      "id": "f4fba8aa-aab5-476c-8d3e-1acc4bb9636e",
      "artistName": "Jéssica Gaspar",
      "imageUrl": "https://i.scdn.co/image/ab6761610000e5ebe1071279febb6dc14f7ef4b1",
      "spotifyUrl": "https://open.spotify.com/artist/6ungwDo99f5ZK7aNb2UTip",
      "spotifyId": "6ungwDo99f5ZK7aNb2UTip",
      "status": "active",
      "joinedDate": "2025-06-01T21:27:52.079183+00:00"
    },
    {
      "id": "2b8584db-312e-489f-b6e5-4dcb410740f2",
      "artistName": "Jordan Whitlock",
      "imageUrl": "https://i.scdn.co/image/ab6761610000e5eb3bb1d301f2dd42c5d5257c24",
      "spotifyUrl": "https://open.spotify.com/artist/2hfjbY3nRSsfIVyOG5j3Eg",
      "spotifyId": "2hfjbY3nRSsfIVyOG5j3Eg",
      "status": "active",
      "joinedDate": "2025-06-01T21:27:52.079183+00:00"
    },
    {
      "id": "ce57125b-5ff6-4f29-a8a3-a79d414c7194",
      "artistName": "Kali Mija",
      "imageUrl": "https://i.scdn.co/image/ab6761610000e5ebda4c532d652752c4a6799444",
      "spotifyUrl": "https://open.spotify.com/artist/6hMmznEAGabh8UiGkQIuvP",
      "spotifyId": "6hMmznEAGabh8UiGkQIuvP",
      "status": "active",
      "joinedDate": "2025-06-01T21:27:52.079183+00:00"
    },
    {
      "id": "733a694b-a7ee-499b-99ff-87c9961c55cc",
      "artistName": "Klangkiosk.",
      "imageUrl": "https://i.scdn.co/image/ab6761610000e5eb2da1d29c02c8fab0c61bb691",
      "spotifyUrl": "https://open.spotify.com/artist/4ZgaQcX7qFETJjlYNqpwGy",
      "spotifyId": "4ZgaQcX7qFETJjlYNqpwGy",
      "status": "active",
      "joinedDate": "2025-06-01T21:27:52.079183+00:00"
    },
    {
      "id": "a200beaf-3d21-4f5d-acf8-36a82933e3aa",
      "artistName": "Layefa",
      "imageUrl": "https://i.scdn.co/image/ab6761610000e5eb1b4844994d3293d558016255",
      "spotifyUrl": "https://open.spotify.com/artist/7MkQpNkd549FwPBbgkGyE8",
      "spotifyId": "7MkQpNkd549FwPBbgkGyE8",
      "status": "active",
      "joinedDate": "2025-06-01T21:27:52.079183+00:00"
    },
    {
      "id": "a346b791-7b67-4772-a836-64066ce151e5",
      "artistName": "LVCIAN",
      "imageUrl": "https://i.scdn.co/image/ab6761610000e5eb925a36ad618c915dff2a0b00",
      "spotifyUrl": "https://open.spotify.com/artist/3GL5qtBAE5U07CsVrMWx6i",
      "spotifyId": "3GL5qtBAE5U07CsVrMWx6i",
      "status": "active",
      "joinedDate": "2025-06-01T21:27:52.079183+00:00"
    },
    {
      "id": "264cdabb-7516-4aca-9752-cbb080d11bea",
      "artistName": "Mabhani",
      "imageUrl": "https://i.scdn.co/image/ab6761610000e5eb78190c66d5347344b38f35fe",
      "spotifyUrl": "https://open.spotify.com/artist/59u8w3x1IF111bG5y7mAhY",
      "spotifyId": "59u8w3x1IF111bG5y7mAhY",
      "status": "active",
      "joinedDate": "2025-06-01T21:27:52.079183+00:00"
    },
    {
      "id": "ec684c1c-775d-4d82-822a-feb403d4c3ea",
      "artistName": "Maline Aura",
      "imageUrl": "https://i.scdn.co/image/ab6761610000e5eb5259c260eb54728367d7fb9a",
      "spotifyUrl": "https://open.spotify.com/artist/1LcX3ZFNBeGKxkpfCIr4cP",
      "spotifyId": "1LcX3ZFNBeGKxkpfCIr4cP",
      "status": "active",
      "joinedDate": "2025-06-01T21:27:52.079183+00:00"
    },
    {
      "id": "46444a12-b35e-4e29-a1e7-d7a1ec8f051c",
      "artistName": "mohalizer",
      "imageUrl": "https://i.scdn.co/image/ab6761610000e5eb572a2c748cf9d08a1a74f5ac",
      "spotifyUrl": "https://open.spotify.com/artist/4mxLi0WiovhOvdkqofGO2i",
      "spotifyId": "4mxLi0WiovhOvdkqofGO2i",
      "status": "active",
      "joinedDate": "2025-06-01T21:27:52.079183+00:00"
    },
    {
      "id": "1620f3b0-7025-41ed-80d4-90b30a93a18f",
      "artistName": "Moish",
      "imageUrl": "https://i.scdn.co/image/ab6761610000e5ebf06168681b5ecaeb1ee6ecf1",
      "spotifyUrl": "https://open.spotify.com/artist/250WCtczB5QBdYFXjVZCQ0",
      "spotifyId": "250WCtczB5QBdYFXjVZCQ0",
      "status": "active",
      "joinedDate": "2025-06-01T21:27:52.079183+00:00"
    },
    {
      "id": "809c2323-355f-4ee7-810f-09d1f4824cf2",
      "artistName": "Naarly",
      "imageUrl": "https://i.scdn.co/image/ab6761610000e5eb80ff408f9d1a57213ec771d0",
      "spotifyUrl": "https://open.spotify.com/artist/4ME20XT9IP5JOpqoIGQ6Js",
      "instagramUrl": "https://www.instagram.com/naarl_y/",
      "spotifyId": "4ME20XT9IP5JOpqoIGQ6Js",
      "status": "active",
      "joinedDate": "2025-06-01T21:27:52.079183+00:00"
    },
    {
      "id": "b0c12366-607e-4c2c-b918-03ca16ad8d16",
      "artistName": "Natural Kind",
      "imageUrl": "https://i.scdn.co/image/ab6761610000e5eb2679231f8a49ec2a4a30f534",
      "spotifyUrl": "https://open.spotify.com/artist/0VbZ0nBTckSegXQk1CcIw9",
      "spotifyId": "0VbZ0nBTckSegXQk1CcIw9",
      "status": "active",
      "joinedDate": "2025-06-01T21:27:52.079183+00:00"
    },
    {
      "id": "7ffdfb0a-cbda-458f-8ba1-28647b6ffc24",
      "artistName": "Oladapo",
      "imageUrl": "https://i.scdn.co/image/ab6761610000e5eb18d4c19457fed4d2fe67e645",
      "spotifyUrl": "https://open.spotify.com/artist/6HAro8NBhDtn8csZDPEBuB",
      "spotifyId": "6HAro8NBhDtn8csZDPEBuB",
      "status": "active",
      "joinedDate": "2025-06-01T21:27:52.079183+00:00"
    },
    {
      "id": "f3fc46c6-cd09-4701-8377-781485d5a5ab",
      "artistName": "Papfay",
      "imageUrl": "https://i.scdn.co/image/ab6761610000e5eb6622bba9243754422abbc4c4",
      "spotifyUrl": "https://open.spotify.com/artist/5m1eVPsrnq9Nfvddnn0KSc",
      "spotifyId": "5m1eVPsrnq9Nfvddnn0KSc",
      "status": "active",
      "joinedDate": "2025-06-01T21:27:52.079183+00:00"
    },
    {
      "id": "72c6fda7-bece-4693-a92f-f3f271664035",
      "artistName": "Patrik",
      "imageUrl": "https://i.scdn.co/image/ab6761610000e5ebc651ae231c816dd1f6a9bce1",
      "spotifyUrl": "https://open.spotify.com/artist/6NJpfhDJjOyAHY54nutwTd",
      "spotifyId": "6NJpfhDJjOyAHY54nutwTd",
      "status": "active",
      "joinedDate": "2025-06-01T21:27:52.079183+00:00"
    },
    {
      "id": "f2292b20-dd89-41fa-952a-f8dc19694f46",
      "artistName": "Queenfay",
      "imageUrl": "https://i.scdn.co/image/ab6761610000e5ebff13266d494a43b8830c66ff",
      "spotifyUrl": "https://open.spotify.com/artist/2Fqrep2fvk9K9d3dq4nhVU",
      "spotifyId": "2Fqrep2fvk9K9d3dq4nhVU",
      "status": "active",
      "joinedDate": "2025-06-01T21:27:52.079183+00:00"
    },
    {
      "id": "d6540ad5-aa42-4c40-a308-c6e1e1ff7910",
      "artistName": "Section Five",
      "imageUrl": "https://i.scdn.co/image/ab6761610000e5eb3617fa465bb3267da3f53beb",
      "spotifyUrl": "https://open.spotify.com/artist/5pM2d7Jh0CvXvddLhBsRfS",
      "spotifyId": "5pM2d7Jh0CvXvddLhBsRfS",
      "status": "active",
      "joinedDate": "2025-06-01T21:27:52.079183+00:00"
    },
    {
      "id": "825889e2-10de-4740-bb58-1cc8e4d83e86",
      "artistName": "Sickluv",
      "imageUrl": "https://i.scdn.co/image/ab6761610000e5ebf3e65482293fb9465a38a9bd",
      "spotifyUrl": "https://open.spotify.com/artist/0VKlKyeBQek2wH0MTxUuWe",
      "instagramUrl": "https://www.instagram.com/sickluv_music/",
      "spotifyId": "0VKlKyeBQek2wH0MTxUuWe",
      "status": "active",
      "joinedDate": "2025-06-01T21:27:52.079183+00:00"
    },
    {
      "id": "537938d3-7524-483b-8e01-611b3931e4c8",
      "artistName": "Silvva",
      "imageUrl": "https://i.scdn.co/image/ab6761610000e5eb09428a4cff898d410c1762ad",
      "spotifyUrl": "https://open.spotify.com/artist/6lsUhJ5WPUsl8ZKVMndV0g",
      "instagramUrl": "https://www.instagram.com/silvva_ofc/",
      "spotifyId": "6lsUhJ5WPUsl8ZKVMndV0g",
      "status": "active",
      "joinedDate": "2025-06-01T21:27:52.079183+00:00"
    },
    {
      "id": "647eb4fc-a016-41c5-864a-a588df64f1b7",
      "artistName": "Skye Wanda",
      "imageUrl": "https://i.scdn.co/image/ab6761610000e5eb61333d9e8c4aeec785fbd1d7",
      "spotifyUrl": "https://open.spotify.com/artist/7BwrJs4E8L2r4FiavhNFa1",
      "spotifyId": "7BwrJs4E8L2r4FiavhNFa1",
      "status": "active",
      "joinedDate": "2025-06-01T21:27:52.079183+00:00"
    },
    {
      "id": "1d974342-7664-4a28-884d-973fed56de6d",
      "artistName": "Slow Ted",
      "imageUrl": "https://i.scdn.co/image/ab6761610000e5eb5137e26a6baca00f84a3fc52",
      "spotifyUrl": "https://open.spotify.com/artist/7gU4zqbpqWECGMnox5c9G8",
      "spotifyId": "7gU4zqbpqWECGMnox5c9G8",
      "status": "active",
      "joinedDate": "2025-06-01T21:27:52.079183+00:00"
    },
    {
      "id": "9d0233d9-c148-412f-bc36-7d9176da379c",
      "artistName": "Thabza De Soul",
      "imageUrl": "https://i.scdn.co/image/ab6761610000e5eba49f47be2365309aee548f88",
      "spotifyUrl": "https://open.spotify.com/artist/3FCL7AQnXR5pCWrceDPFhH",
      "spotifyId": "3FCL7AQnXR5pCWrceDPFhH",
      "status": "active",
      "joinedDate": "2025-06-01T21:27:52.079183+00:00"
    },
    {
      "id": "d4165c56-78cf-4d68-a7aa-de1241621f0d",
      "artistName": "The Fold",
      "imageUrl": "https://i.scdn.co/image/ab6761610000e5ebcffb2ea0093af7c4f9504e83",
      "spotifyUrl": "https://open.spotify.com/artist/0oNO9qtlsl8sCfZUR3yLz8",
      "spotifyId": "0oNO9qtlsl8sCfZUR3yLz8",
      "status": "active",
      "joinedDate": "2025-06-01T21:27:52.079183+00:00"
    },
    {
      "id": "4eaaadfb-e805-46f0-9c65-4470a08bd356",
      "artistName": "Vic Laos",
      "imageUrl": "https://i.scdn.co/image/ab6761610000e5eb9cccbb23a58bc7afb74b2aaa",
      "spotifyUrl": "https://open.spotify.com/artist/2AfOxybw9BWMYy0PqvQwYF",
      "spotifyId": "2AfOxybw9BWMYy0PqvQwYF",
      "status": "active",
      "joinedDate": "2025-06-01T21:27:52.079183+00:00"
    },
    {
      "id": "91b592f4-ccb5-4110-bb58-a18b640a81a5",
      "artistName": "VIKS",
      "imageUrl": "https://i.scdn.co/image/ab6761610000e5eb0c36c772f064f443c4ff1082",
      "spotifyUrl": "https://open.spotify.com/artist/7qRgPiAQ03LCU27CHg4BpE",
      "spotifyId": "7qRgPiAQ03LCU27CHg4BpE",
      "status": "active",
      "joinedDate": "2025-06-01T21:27:52.079183+00:00"
    },
    {
      "id": "ca8bedd0-89d5-4e28-ba2d-5ea93151492a",
      "artistName": "Village Guru",
      "imageUrl": "https://i.scdn.co/image/ab6761610000e5eba7c35b07defd7a518ade6647",
      "spotifyUrl": "https://open.spotify.com/artist/0ovC1rRwQ50OEVoyg271k0",
      "spotifyId": "0ovC1rRwQ50OEVoyg271k0",
      "status": "active",
      "joinedDate": "2025-06-01T21:27:52.079183+00:00"
    },
    {
      "id": "b23cb5ef-fd49-4ea3-bc37-72aaa763ef9d",
      "artistName": "Vinnie Mak",
      "imageUrl": "https://i.scdn.co/image/ab67616d0000b2736947cd925ea9463b3d509303",
      "spotifyUrl": "https://open.spotify.com/artist/1gOP3ZR52ZQpJiMFCGHfhC",
      "spotifyId": "1gOP3ZR52ZQpJiMFCGHfhC",
      "status": "active",
      "joinedDate": "2025-06-01T21:27:52.079183+00:00"
    },
    {
      "id": "b0726cfb-f1cc-4939-8c7f-f27b88556454",
      "artistName": "Voig Leicam",
      "imageUrl": "https://i.scdn.co/image/ab6761610000e5ebbef5d4d4c2d21d7ba176386e",
      "spotifyUrl": "https://open.spotify.com/artist/48IHlLbs871u3FyRsSrq5G",
      "spotifyId": "48IHlLbs871u3FyRsSrq5G",
      "status": "active",
      "joinedDate": "2025-06-01T21:27:52.079183+00:00"
    },
    {
      "id": "e1e57f3e-6c3f-4205-8cff-997a8f86319b",
      "artistName": "whereisvero",
      "imageUrl": "https://i.scdn.co/image/ab6761610000e5eb89c2a7eaaac9006ef793d4a6",
      "spotifyUrl": "https://open.spotify.com/artist/6x9CKUBQ96VjXxKgGE5hIw",
      "instagramUrl": "https://www.instagram.com/whereisvero/",
      "status": "active",
      "joinedDate": "2025-06-01T21:27:52.079183+00:00"
    },
    {
      "id": "9fd72901-8765-4e21-b8ff-b1f4aaa16e1c",
      "artistName": "Winterkind",
      "imageUrl": "https://i.scdn.co/image/ab6761610000e5eb82c0bd37287390a43cb11923",
      "spotifyUrl": "https://open.spotify.com/artist/5pN40wGpDTFEuHTvndL1wf",
      "spotifyId": "5pN40wGpDTFEuHTvndL1wf",
      "status": "active",
      "joinedDate": "2025-06-01T21:27:52.079183+00:00"
    }
  ],
  "metadata": {
    "totalArtists": 51,
    "lastUpdated": "2025-06-05T23:21:15.169Z",
    "format": "detailed",
    "includeInactive": false
  }
}
